{
  "0":{
    "sales":{
      "transaction":{
        "id":"0xc87acf4217057c5299d0170d063010fdee823235fd45066a363dc20c43ebb8a1",
        "transfers":[
          {
            "senderAddress":{
              "id":"0x7143fbf7cf066ba2390eb66f309999019b34aafe"
            },
            "receiverAddress":{
              "id":"0xf4ae4026f3e9f31bd830b5093122dc38cc04616a"
            },
            "amount":"0.04975",
            "token":{
              "collection":{
                "symbol":"TAISTC",
                "name":"This Artwork Is Subject To Change"
              }
            }
          }
        ],
        "transactionFrom":"0xf4ae4026f3e9f31bd830b5093122dc38cc04616a"
      },
      "platform":"X2Y2",
      "amount":"0.04975",
      "currency":{
        "name":"Ether",
        "symbol":"ETH"
      },
      "timestamp":1677128291,
      "blockNumber":16688870
    }
  },
  "1":{
    "sales":{
      "transaction":{
        "id":"0x8803146e89fc6c76f1d72f7ab48986914af950c76f39a565facad132efb24d10",
        "transfers":[
          {
            "senderAddress":{
              "id":"0x620334a2a05ac5e7c13cd12c4bb414a71c47ebce"
            },
            "receiverAddress":{
              "id":"0x9ebfb53fa8526906738856848a27cb11b0285c3f"
            },
            "amount":"0.01015306122448979591836734693877551",
            "token":{
              "collection":{
                "symbol":"ZORB",
                "name":"Zorbs"
              }
            }
          },
          {
            "senderAddress":{
              "id":"0x9ebfb53fa8526906738856848a27cb11b0285c3f"
            },
            "receiverAddress":{
              "id":"0xac992da07e0227d9e999e8a149945b3361ba8043"
            },
            "amount":"0",
            "token":{
              "collection":{
                "symbol":"ZORB",
                "name":"Zorbs"
              }
            }
          }
        ],
        "transactionFrom":"0xac992da07e0227d9e999e8a149945b3361ba8043"
      },
      "platform":"X2Y2",
      "amount":"0.01015306122448979591836734693877551",
      "currency":{
        "name":"Ether",
        "symbol":"ETH"
      },
      "timestamp":1677128411,
      "blockNumber":16688880
    }
  },
  "2":{
    "sales":{
      "transaction":{
        "id":"0x0706447c2e5bf524bbf2e09add561c41fc961f01cbb102d50aa80a689e630104",
        "transfers":[
          {
            "senderAddress":{
              "id":"0x331e1ba82b52b88c5ac9f920be978b8f5c171d36"
            },
            "receiverAddress":{
              "id":"0x012b38ccb3ae97a32cd24088bf9426d4ee5442d3"
            },
            "amount":"10.38775510204081632653061224489796",
            "token":{
              "collection":{
                "symbol":"KZG",
                "name":"Keungz Genesis"
              }
            }
          }
        ],
        "transactionFrom":"0x012b38ccb3ae97a32cd24088bf9426d4ee5442d3"
      },
      "platform":"X2Y2",
      "amount":"10.38775510204081632653061224489796",
      "currency":{
        "name":"Ether",
        "symbol":"ETH"
      },
      "timestamp":1677128567,
      "blockNumber":16688893
    }
  },
  "3":{
    "sales":{
      "transaction":{
        "id":"0xb05e8363dfe8b54f556762b31a1357be80afd0581589b44d8ee2e3801c927c01",
        "transfers":[
          {
            "senderAddress":{
              "id":"0xc409de9b341dbac065359cf053c3572e4976531b"
            },
            "receiverAddress":{
              "id":"0xcb8c1fe534aafa4f1e7036ea0d33fc86d1e7e403"
            },
            "amount":"0.076715",
            "token":{
              "collection":{
                "symbol":"SPR",
                "name":"Space Riders"
              }
            }
          }
        ],
        "transactionFrom":"0xc409de9b341dbac065359cf053c3572e4976531b"
      },
      "platform":"LooksRare",
      "amount":"0.076715",
      "currency":{
        "name":"Wrapped Ether",
        "symbol":"WETH"
      },
      "timestamp":1677128867,
      "blockNumber":16688918
    }
  },
  "4":{
    "sales":{
      "transaction":{
        "id":"0x01797147e8a538ebb6a137aac95e828cd30fbf43504bc5499878123928dab39a",
        "transfers":[
          {
            "senderAddress":{
              "id":"0x4e258cc6180e73a69bb0ce18621c8901aed3b792"
            },
            "receiverAddress":{
              "id":"0x7526a5a93e82f18a0f342ec63278494758965a08"
            },
            "amount":"0.01522959183673469387755102040816327",
            "token":{
              "collection":{
                "symbol":"Minds",
                "name":"200 Minds By Moth Fund"
              }
            }
          }
        ],
        "transactionFrom":"0x7526a5a93e82f18a0f342ec63278494758965a08"
      },
      "platform":"X2Y2",
      "amount":"0.01522959183673469387755102040816327",
      "currency":{
        "name":"Ether",
        "symbol":"ETH"
      },
      "timestamp":1677128963,
      "blockNumber":16688926
    }
  },
  "5":{
    "sales":{
      "transaction":{
        "id":"0x33f3874f0c4025869a3a0673a98983ce14027595e92d19c7d021a95fafe170bc",
        "transfers":[
          {
            "senderAddress":{
              "id":"0x1618406d203aefa14526f77d79fdbeac9d42137b"
            },
            "receiverAddress":{
              "id":"0xd9d7046933bd3d0a3e869959ef95e4c41522c1bf"
            },
            "amount":"3.571428571428571428571428571428571",
            "token":{
              "collection":{
                "symbol":"OTHR",
                "name":"Otherdeed"
              }
            }
          }
        ],
        "transactionFrom":"0xd9d7046933bd3d0a3e869959ef95e4c41522c1bf"
      },
      "platform":"X2Y2",
      "amount":"3.571428571428571428571428571428571",
      "currency":{
        "name":"Ether",
        "symbol":"ETH"
      },
      "timestamp":1677129371,
      "blockNumber":16688960
    }
  },
  "6":{
    "sales":{
      "transaction":{
        "id":"0x2ca234a77ea500401bbfe256ab86f769cb584fd92d7705d115a7ef490c5f1f3b",
        "transfers":[
          {
            "senderAddress":{
              "id":"0xf4d631fa4cb9322366bd5ebc25ea94dfce1ddf09"
            },
            "receiverAddress":{
              "id":"0x5284ade3f5b950d181fc93372950f3b389d28ee3"
            },
            "amount":"0.1810706785714285714285714285714286",
            "token":{
              "collection":{
                "symbol":"KPRV2",
                "name":"Keepers V2"
              }
            }
          }
        ],
        "transactionFrom":"0x5284ade3f5b950d181fc93372950f3b389d28ee3"
      },
      "platform":"X2Y2",
      "amount":"0.1810706785714285714285714285714286",
      "currency":{
        "name":"Ether",
        "symbol":"ETH"
      },
      "timestamp":1677129563,
      "blockNumber":16688976
    }
  },
  "7":{
    "sales":{
      "transaction":{
        "id":"0xc89b8ef9ad673f79c233517c855bb8a7c6b9ae53cf4a71c552078066b8eb6b06",
        "transfers":[
          {
            "senderAddress":{
              "id":"0xebd7c0190a0fcc17f34f396e89870372c66d2901"
            },
            "receiverAddress":{
              "id":"0x67a3291dc993cb2fd4079bb91e8a756c64a5c682"
            },
            "amount":"0.4285714285714285714285714285714286",
            "token":{
              "collection":{
                "symbol":"GU",
                "name":"Genuine Undead"
              }
            }
          }
        ],
        "transactionFrom":"0x67a3291dc993cb2fd4079bb91e8a756c64a5c682"
      },
      "platform":"X2Y2",
      "amount":"0.4285714285714285714285714285714286",
      "currency":{
        "name":"Ether",
        "symbol":"ETH"
      },
      "timestamp":1677129623,
      "blockNumber":16688981
    }
  },
  "8":{
    "sales":{
      "transaction":{
        "id":"0x534887922f927c40f698967c4beca4e405fc0232cf468ca7a3411f058741e2d9",
        "transfers":[
          {
            "senderAddress":{
              "id":"0x6e5839ae97f29910d8fd9ffb380c575e9b055500"
            },
            "receiverAddress":{
              "id":"0x56dd5bbede9bfdb10a2845c4d70d4a2950163044"
            },
            "amount":"0.009137755102040816326530612244897959",
            "token":{
              "collection":{
                "symbol":"BPR",
                "name":"BluePrint Robots"
              }
            }
          },
          {
            "senderAddress":{
              "id":"0x6e5839ae97f29910d8fd9ffb380c575e9b055500"
            },
            "receiverAddress":{
              "id":"0x56dd5bbede9bfdb10a2845c4d70d4a2950163044"
            },
            "amount":"0.009137755102040816326530612244897959",
            "token":{
              "collection":{
                "symbol":"BPR",
                "name":"BluePrint Robots"
              }
            }
          },
          {
            "senderAddress":{
              "id":"0x56dd5bbede9bfdb10a2845c4d70d4a2950163044"
            },
            "receiverAddress":{
              "id":"0x9d6061f52b2a1032dc396066350c57b8ba4da430"
            },
            "amount":"0",
            "token":{
              "collection":{
                "symbol":"BPR",
                "name":"BluePrint Robots"
              }
            }
          },
          {
            "senderAddress":{
              "id":"0x56dd5bbede9bfdb10a2845c4d70d4a2950163044"
            },
            "receiverAddress":{
              "id":"0x9d6061f52b2a1032dc396066350c57b8ba4da430"
            },
            "amount":"0",
            "token":{
              "collection":{
                "symbol":"BPR",
                "name":"BluePrint Robots"
              }
            }
          }
        ],
        "transactionFrom":"0x9d6061f52b2a1032dc396066350c57b8ba4da430"
      },
      "platform":"X2Y2",
      "amount":"0.009137755102040816326530612244897959",
      "currency":{
        "name":"Ether",
        "symbol":"ETH"
      },
      "timestamp":1677129731,
      "blockNumber":16688990
    }
  },
  "9":{
    "sales":{
      "transaction":{
        "id":"0x534887922f927c40f698967c4beca4e405fc0232cf468ca7a3411f058741e2d9",
        "transfers":[
          {
            "senderAddress":{
              "id":"0x6e5839ae97f29910d8fd9ffb380c575e9b055500"
            },
            "receiverAddress":{
              "id":"0x56dd5bbede9bfdb10a2845c4d70d4a2950163044"
            },
            "amount":"0.009137755102040816326530612244897959",
            "token":{
              "collection":{
                "symbol":"BPR",
                "name":"BluePrint Robots"
              }
            }
          },
          {
            "senderAddress":{
              "id":"0x6e5839ae97f29910d8fd9ffb380c575e9b055500"
            },
            "receiverAddress":{
              "id":"0x56dd5bbede9bfdb10a2845c4d70d4a2950163044"
            },
            "amount":"0.009137755102040816326530612244897959",
            "token":{
              "collection":{
                "symbol":"BPR",
                "name":"BluePrint Robots"
              }
            }
          },
          {
            "senderAddress":{
              "id":"0x56dd5bbede9bfdb10a2845c4d70d4a2950163044"
            },
            "receiverAddress":{
              "id":"0x9d6061f52b2a1032dc396066350c57b8ba4da430"
            },
            "amount":"0",
            "token":{
              "collection":{
                "symbol":"BPR",
                "name":"BluePrint Robots"
              }
            }
          },
          {
            "senderAddress":{
              "id":"0x56dd5bbede9bfdb10a2845c4d70d4a2950163044"
            },
            "receiverAddress":{
              "id":"0x9d6061f52b2a1032dc396066350c57b8ba4da430"
            },
            "amount":"0",
            "token":{
              "collection":{
                "symbol":"BPR",
                "name":"BluePrint Robots"
              }
            }
          }
        ],
        "transactionFrom":"0x9d6061f52b2a1032dc396066350c57b8ba4da430"
      },
      "platform":"X2Y2",
      "amount":"0.009137755102040816326530612244897959",
      "currency":{
        "name":"Ether",
        "symbol":"ETH"
      },
      "timestamp":1677129731,
      "blockNumber":16688990
    }
  },
  "10":{
    "sales":{
      "transaction":{
        "id":"0xf75ff3f71c25546e7a6d8d14073eda4bc22f6dd911dd0231e816f2ebc30dfa40",
        "transfers":[
          {
            "senderAddress":{
              "id":"0x5a1d4bb2b63cc7d590b1d1cf9bf48e83d42ffb42"
            },
            "receiverAddress":{
              "id":"0x906b7e8c4fd8ae6e8112797f15fc4253073c2b4d"
            },
            "amount":"0.9825",
            "token":{
              "collection":{
                "symbol":"OTHR",
                "name":"Otherdeed"
              }
            }
          },
          {
            "senderAddress":{
              "id":"0x906b7e8c4fd8ae6e8112797f15fc4253073c2b4d"
            },
            "receiverAddress":{
              "id":"0x92e44b9368afe8e7e8cf9ca102e969f5e63dcb21"
            },
            "amount":"0.9825",
            "token":{
              "collection":{
                "symbol":"OTHR",
                "name":"Otherdeed"
              }
            }
          }
        ],
        "transactionFrom":"0xeff711657ff5260cb2a35dbe9cd2dca867089531"
      },
      "platform":"LooksRare",
      "amount":"1.965",
      "currency":{
        "name":"Wrapped Ether",
        "symbol":"WETH"
      },
      "timestamp":1677130031,
      "blockNumber":16689014
    }
  },
  "11":{
    "sales":{
      "transaction":{
        "id":"0x52f3dc519606ecddb3f5199817451a8cddba69978ac1a985947084ca199140de",
        "transfers":[
          {
            "senderAddress":{
              "id":"0xf05266681fccdecad4e69566405716d4b9bae599"
            },
            "receiverAddress":{
              "id":"0x1d60970b84199c58a4406be4e482084e80dd77de"
            },
            "amount":"0.1015306122448979591836734693877551",
            "token":{
              "collection":{
                "symbol":"ABS",
                "name":"Adam Bomb Squad"
              }
            }
          }
        ],
        "transactionFrom":"0xf05266681fccdecad4e69566405716d4b9bae599"
      },
      "platform":"X2Y2",
      "amount":"0.1015306122448979591836734693877551",
      "currency":{
        "name":"Wrapped Ether",
        "symbol":"WETH"
      },
      "timestamp":1677130391,
      "blockNumber":16689044
    }
  },
  "12":{
    "sales":{
      "transaction":{
        "id":"0xba05943ba78db95078c82ed4b0e9c039e7207e0995e7cb03cc710f2bb5dc89a4",
        "transfers":[
          {
            "senderAddress":{
              "id":"0x620334a2a05ac5e7c13cd12c4bb414a71c47ebce"
            },
            "receiverAddress":{
              "id":"0x613d3c588f6b8f89302b463f8f19f7241b2857e2"
            },
            "amount":"0.01015306122448979591836734693877551",
            "token":{
              "collection":{
                "symbol":"ZORB",
                "name":"Zorbs"
              }
            }
          },
          {
            "senderAddress":{
              "id":"0x613d3c588f6b8f89302b463f8f19f7241b2857e2"
            },
            "receiverAddress":{
              "id":"0x747811193cd339582929344c74e315339db57446"
            },
            "amount":"0",
            "token":{
              "collection":{
                "symbol":"ZORB",
                "name":"Zorbs"
              }
            }
          }
        ],
        "transactionFrom":"0x747811193cd339582929344c74e315339db57446"
      },
      "platform":"X2Y2",
      "amount":"0.01015306122448979591836734693877551",
      "currency":{
        "name":"Ether",
        "symbol":"ETH"
      },
      "timestamp":1677130511,
      "blockNumber":16689054
    }
  },
  "13":{
    "sales":{
      "transaction":{
        "id":"0xded57ca8753de51bfcf832f1c4fbd78a53f8f46204090b8bde9bd68f6308ccd9",
        "transfers":[
          {
            "senderAddress":{
              "id":"0x7195aac46d676e51f2044bc5b77f4b612918edb2"
            },
            "receiverAddress":{
              "id":"0xe6c227b29965f94aa0a76b8213aeb3017dd7e69b"
            },
            "amount":"0.004719387755102040816326530612244898",
            "token":{
              "collection":{
                "symbol":"EC",
                "name":"ET-Cat"
              }
            }
          }
        ],
        "transactionFrom":"0xe6c227b29965f94aa0a76b8213aeb3017dd7e69b"
      },
      "platform":"X2Y2",
      "amount":"0.004719387755102040816326530612244898",
      "currency":{
        "name":"Ether",
        "symbol":"ETH"
      },
      "timestamp":1677130667,
      "blockNumber":16689067
    }
  },
  "14":{
    "sales":{
      "transaction":{
        "id":"0xe4dc38d42b370f16f561905605fbc25c6ddb356c0fb4cc3bf826ebbcd972795a",
        "transfers":[
          {
            "senderAddress":{
              "id":"0x43c922deb0827b9f5b1bac648677077a66f108e5"
            },
            "receiverAddress":{
              "id":"0xbb718c12ac938152ed1fb1b3e330f88fc1eb424d"
            },
            "amount":"16.2",
            "token":{
              "collection":{
                "symbol":"MAYC",
                "name":"MutantApeYachtClub"
              }
            }
          }
        ],
        "transactionFrom":"0x43c922deb0827b9f5b1bac648677077a66f108e5"
      },
      "platform":"LooksRare",
      "amount":"16.2",
      "currency":{
        "name":"Wrapped Ether",
        "symbol":"WETH"
      },
      "timestamp":1677130715,
      "blockNumber":16689071
    }
  },
  "15":{
    "sales":{
      "transaction":{
        "id":"0x7022059cb589b15206faf34646338fda7acf6a538c393915ee16079c0c77582f",
        "transfers":[
          {
            "senderAddress":{
              "id":"0x562607a01a12e84a4abe025ac14ab1e36b76519f"
            },
            "receiverAddress":{
              "id":"0x7ec5385d28868155b22da4c8bb5ad7ea2036104f"
            },
            "amount":"0.1465",
            "token":{
              "collection":{
                "symbol":"IVYBOYS",
                "name":"BBRC OFFICIAL - IVY BOYS"
              }
            }
          },
          {
            "senderAddress":{
              "id":"0x7ec5385d28868155b22da4c8bb5ad7ea2036104f"
            },
            "receiverAddress":{
              "id":"0x3bed6c7ec492d0d57f68f8c402fb7e2de51c1165"
            },
            "amount":"0",
            "token":{
              "collection":{
                "symbol":"IVYBOYS",
                "name":"BBRC OFFICIAL - IVY BOYS"
              }
            }
          }
        ],
        "transactionFrom":"0xe888e6009ee7f4cc7b9d4096a41053cbc2daaa4d"
      },
      "platform":"LooksRare",
      "amount":"0.1465",
      "currency":{
        "name":"Wrapped Ether",
        "symbol":"WETH"
      },
      "timestamp":1677130787,
      "blockNumber":16689077
    }
  },
  "16":{
    "sales":{
      "transaction":{
        "id":"0xff191010a43ddb6f6b2f8c957982937118633490341724e914dd155bed5e98a8",
        "transfers":[
          {
            "senderAddress":{
              "id":"0x7195aac46d676e51f2044bc5b77f4b612918edb2"
            },
            "receiverAddress":{
              "id":"0x4326275317acc0fae4aa5c68fce4c54c74dc08d3"
            },
            "amount":"0.004719387755102040816326530612244898",
            "token":{
              "collection":{
                "symbol":"EC",
                "name":"ET-Cat"
              }
            }
          },
          {
            "senderAddress":{
              "id":"0x4326275317acc0fae4aa5c68fce4c54c74dc08d3"
            },
            "receiverAddress":{
              "id":"0xb77a12542203e5b4b26e1cbaf7a6223fdf001e67"
            },
            "amount":"0.002359693877551020408163265306122449",
            "token":{
              "collection":{
                "symbol":"EC",
                "name":"ET-Cat"
              }
            }
          },
          {
            "senderAddress":{
              "id":"0x7195aac46d676e51f2044bc5b77f4b612918edb2"
            },
            "receiverAddress":{
              "id":"0x4326275317acc0fae4aa5c68fce4c54c74dc08d3"
            },
            "amount":"0.002359693877551020408163265306122449",
            "token":{
              "collection":{
                "symbol":"EC",
                "name":"ET-Cat"
              }
            }
          },
          {
            "senderAddress":{
              "id":"0x4326275317acc0fae4aa5c68fce4c54c74dc08d3"
            },
            "receiverAddress":{
              "id":"0xb77a12542203e5b4b26e1cbaf7a6223fdf001e67"
            },
            "amount":"0",
            "token":{
              "collection":{
                "symbol":"EC",
                "name":"ET-Cat"
              }
            }
          }
        ],
        "transactionFrom":"0xb77a12542203e5b4b26e1cbaf7a6223fdf001e67"
      },
      "platform":"X2Y2",
      "amount":"0.004719387755102040816326530612244898",
      "currency":{
        "name":"Ether",
        "symbol":"ETH"
      },
      "timestamp":1677130871,
      "blockNumber":16689083
    }
  },
  "17":{
    "sales":{
      "transaction":{
        "id":"0xff191010a43ddb6f6b2f8c957982937118633490341724e914dd155bed5e98a8",
        "transfers":[
          {
            "senderAddress":{
              "id":"0x7195aac46d676e51f2044bc5b77f4b612918edb2"
            },
            "receiverAddress":{
              "id":"0x4326275317acc0fae4aa5c68fce4c54c74dc08d3"
            },
            "amount":"0.004719387755102040816326530612244898",
            "token":{
              "collection":{
                "symbol":"EC",
                "name":"ET-Cat"
              }
            }
          },
          {
            "senderAddress":{
              "id":"0x4326275317acc0fae4aa5c68fce4c54c74dc08d3"
            },
            "receiverAddress":{
              "id":"0xb77a12542203e5b4b26e1cbaf7a6223fdf001e67"
            },
            "amount":"0.002359693877551020408163265306122449",
            "token":{
              "collection":{
                "symbol":"EC",
                "name":"ET-Cat"
              }
            }
          },
          {
            "senderAddress":{
              "id":"0x7195aac46d676e51f2044bc5b77f4b612918edb2"
            },
            "receiverAddress":{
              "id":"0x4326275317acc0fae4aa5c68fce4c54c74dc08d3"
            },
            "amount":"0.002359693877551020408163265306122449",
            "token":{
              "collection":{
                "symbol":"EC",
                "name":"ET-Cat"
              }
            }
          },
          {
            "senderAddress":{
              "id":"0x4326275317acc0fae4aa5c68fce4c54c74dc08d3"
            },
            "receiverAddress":{
              "id":"0xb77a12542203e5b4b26e1cbaf7a6223fdf001e67"
            },
            "amount":"0",
            "token":{
              "collection":{
                "symbol":"EC",
                "name":"ET-Cat"
              }
            }
          }
        ],
        "transactionFrom":"0xb77a12542203e5b4b26e1cbaf7a6223fdf001e67"
      },
      "platform":"X2Y2",
      "amount":"0.004719387755102040816326530612244898",
      "currency":{
        "name":"Ether",
        "symbol":"ETH"
      },
      "timestamp":1677130871,
      "blockNumber":16689083
    }
  },
  "18":{
    "sales":{
      "transaction":{
        "id":"0xafac6d96a766e60e24d45d2719c659312fadd1af413175478d8ceaef300d58df",
        "transfers":[
          {
            "senderAddress":{
              "id":"0x43c922deb0827b9f5b1bac648677077a66f108e5"
            },
            "receiverAddress":{
              "id":"0x7125925f66da4f01d89eaa8aca27e0e34291812c"
            },
            "amount":"0.104618965805070511",
            "token":{
              "collection":{
                "symbol":"KGF",
                "name":"Killer GF"
              }
            }
          }
        ],
        "transactionFrom":"0x43c922deb0827b9f5b1bac648677077a66f108e5"
      },
      "platform":"LooksRare",
      "amount":"0.104618965805070511",
      "currency":{
        "name":"Wrapped Ether",
        "symbol":"WETH"
      },
      "timestamp":1677130883,
      "blockNumber":16689084
    }
  },
  "19":{
    "sales":{
      "transaction":{
        "id":"0x3eed558c9deccc00b03194c99fe6601e3134e661c8d514614f50d826cce170d0",
        "transfers":[
          {
            "senderAddress":{
              "id":"0x3b81fa4ec1af989545b5fb9130a29dd29976797b"
            },
            "receiverAddress":{
              "id":"0x172458ff1b115ba5c2076465977baf6152c5ac72"
            },
            "amount":"0.04558724489795918367346938775510204",
            "token":{
              "collection":{
                "symbol":"TAISTC",
                "name":"This Artwork Is Subject To Change"
              }
            }
          }
        ],
        "transactionFrom":"0x172458ff1b115ba5c2076465977baf6152c5ac72"
      },
      "platform":"X2Y2",
      "amount":"0.04558724489795918367346938775510204",
      "currency":{
        "name":"Ether",
        "symbol":"ETH"
      },
      "timestamp":1677131171,
      "blockNumber":16689108
    }
  },
  "20":{
    "sales":{
      "transaction":{
        "id":"0xa254354ec468c147c55f33004687dc68c42748e9aca290f06bd1842ef46f5ae0",
        "transfers":[
          {
            "senderAddress":{
              "id":"0x3e8ff86ebe357d4e222f03144ea5d22dc40093b2"
            },
            "receiverAddress":{
              "id":"0x0000008682fa8c3aa14b11894e90e3dcbbff715b"
            },
            "amount":"0.012030000005",
            "token":{
              "collection":{
                "symbol":"EDITIONS_V3",
                "name":"Mirror Editions V3"
              }
            }
          },
          {
            "senderAddress":{
              "id":"0x0000008682fa8c3aa14b11894e90e3dcbbff715b"
            },
            "receiverAddress":{
              "id":"0xedbe6ed3426e6c12bf1d1cd4ba06cc620d0800f1"
            },
            "amount":"0.012030000005",
            "token":{
              "collection":{
                "symbol":"EDITIONS_V3",
                "name":"Mirror Editions V3"
              }
            }
          }
        ],
        "transactionFrom":"0xbce31af175dfc6be46d93665ab2022ec9420ac57"
      },
      "platform":"LooksRare",
      "amount":"0.02406000001",
      "currency":{
        "name":"Wrapped Ether",
        "symbol":"WETH"
      },
      "timestamp":1677131219,
      "blockNumber":16689112
    }
  },
  "21":{
    "sales":{
      "transaction":{
        "id":"0xbbb40bec6a221c246f47bdc9bed7fe3394bf70b79a26058a9727c431b4be38c9",
        "transfers":[
          {
            "senderAddress":{
              "id":"0x7195aac46d676e51f2044bc5b77f4b612918edb2"
            },
            "receiverAddress":{
              "id":"0x08405c12459c190d2e83e059e774f9985c1763a4"
            },
            "amount":"0.006135204081632653061224489795918367",
            "token":{
              "collection":{
                "symbol":"EC",
                "name":"ET-Cat"
              }
            }
          }
        ],
        "transactionFrom":"0x08405c12459c190d2e83e059e774f9985c1763a4"
      },
      "platform":"X2Y2",
      "amount":"0.006135204081632653061224489795918367",
      "currency":{
        "name":"Ether",
        "symbol":"ETH"
      },
      "timestamp":1677131279,
      "blockNumber":16689117
    }
  },
  "22":{
    "sales":{
      "transaction":{
        "id":"0x9491208054ad72cb5fdcb043e2ad4799a2ca5b621e5394ae25187e28f78b4374",
        "transfers":[
          {
            "senderAddress":{
              "id":"0x3e8ff86ebe357d4e222f03144ea5d22dc40093b2"
            },
            "receiverAddress":{
              "id":"0x00000000d3baaa99a7e09ad0cd6efa987484064f"
            },
            "amount":"0.012030000005",
            "token":{
              "collection":{
                "symbol":"EDITIONS_V3",
                "name":"Mirror Editions V3"
              }
            }
          },
          {
            "senderAddress":{
              "id":"0x00000000d3baaa99a7e09ad0cd6efa987484064f"
            },
            "receiverAddress":{
              "id":"0x4bccc930ce07d1d6fdd55f19caef13477b23ada0"
            },
            "amount":"0.012030000005",
            "token":{
              "collection":{
                "symbol":"EDITIONS_V3",
                "name":"Mirror Editions V3"
              }
            }
          }
        ],
        "transactionFrom":"0x528ce4b72ff44ab0b60d624726295ed1c5235199"
      },
      "platform":"LooksRare",
      "amount":"0.02406000001",
      "currency":{
        "name":"Wrapped Ether",
        "symbol":"WETH"
      },
      "timestamp":1677131399,
      "blockNumber":16689127
    }
  },
  "23":{
    "sales":{
      "transaction":{
        "id":"0xb87ae0f47cbf95525f7f2f05b114bddc8e10745a20c07d4c7e7e73253dd4b8db",
        "transfers":[
          {
            "senderAddress":{
              "id":"0xd722755aa3d8b2e9521209ee5014d0e446b82ff5"
            },
            "receiverAddress":{
              "id":"0xb5bb09ecaecb7fca6c837ab706ce321b3a3dd949"
            },
            "amount":"0.0369",
            "token":{
              "collection":{
                "symbol":"LAYC",
                "name":"Lazy Ape Yacht Club"
              }
            }
          }
        ],
        "transactionFrom":"0xb5bb09ecaecb7fca6c837ab706ce321b3a3dd949"
      },
      "platform":"LooksRare",
      "amount":"0.0369",
      "currency":{
        "name":"Wrapped Ether",
        "symbol":"WETH"
      },
      "timestamp":1677131543,
      "blockNumber":16689139
    }
  },
  "24":{
    "sales":{
      "transaction":{
        "id":"0xbbc8957b0ef4697163fcc30238f5b63c7aebb5bc21b9c013d947177d9ef6fcbe",
        "transfers":[
          {
            "senderAddress":{
              "id":"0xef528c12d521b5d7ea5c287b84c4ea682114a6d6"
            },
            "receiverAddress":{
              "id":"0xf6a027de6425fc47c6d9860805800ec4ab276803"
            },
            "amount":"0.05106989795918367346938775510204082",
            "token":{
              "collection":{
                "symbol":"TAISTC",
                "name":"This Artwork Is Subject To Change"
              }
            }
          }
        ],
        "transactionFrom":"0xf6a027de6425fc47c6d9860805800ec4ab276803"
      },
      "platform":"X2Y2",
      "amount":"0.05106989795918367346938775510204082",
      "currency":{
        "name":"Ether",
        "symbol":"ETH"
      },
      "timestamp":1677131639,
      "blockNumber":16689147
    }
  },
  "25":{
    "sales":{
      "transaction":{
        "id":"0x96f201446bdb17c5972132c4ae9b76a73c1aac853cdd8a2d1b9396a6fb8ed6f1",
        "transfers":[
          {
            "senderAddress":{
              "id":"0xd722755aa3d8b2e9521209ee5014d0e446b82ff5"
            },
            "receiverAddress":{
              "id":"0x7ec5385d28868155b22da4c8bb5ad7ea2036104f"
            },
            "amount":"0.1455",
            "token":{
              "collection":{
                "symbol":"IVYBOYS",
                "name":"BBRC OFFICIAL - IVY BOYS"
              }
            }
          },
          {
            "senderAddress":{
              "id":"0x7ec5385d28868155b22da4c8bb5ad7ea2036104f"
            },
            "receiverAddress":{
              "id":"0x3bed6c7ec492d0d57f68f8c402fb7e2de51c1165"
            },
            "amount":"0",
            "token":{
              "collection":{
                "symbol":"IVYBOYS",
                "name":"BBRC OFFICIAL - IVY BOYS"
              }
            }
          }
        ],
        "transactionFrom":"0xe888e6009ee7f4cc7b9d4096a41053cbc2daaa4d"
      },
      "platform":"LooksRare",
      "amount":"0.1455",
      "currency":{
        "name":"Wrapped Ether",
        "symbol":"WETH"
      },
      "timestamp":1677131663,
      "blockNumber":16689149
    }
  },
  "26":{
    "sales":{
      "transaction":{
        "id":"0xbc61847a7f9aa94c80c5cdb7e626c3842430100f786deb3f124552398307d311",
        "transfers":[
          {
            "senderAddress":{
              "id":"0xef528c12d521b5d7ea5c287b84c4ea682114a6d6"
            },
            "receiverAddress":{
              "id":"0x4326275317acc0fae4aa5c68fce4c54c74dc08d3"
            },
            "amount":"0.05106989795918367346938775510204082",
            "token":{
              "collection":{
                "symbol":"TAISTC",
                "name":"This Artwork Is Subject To Change"
              }
            }
          },
          {
            "senderAddress":{
              "id":"0x4326275317acc0fae4aa5c68fce4c54c74dc08d3"
            },
            "receiverAddress":{
              "id":"0xfcce36ad3b56647be372f90edaa4864fe32fc4b6"
            },
            "amount":"0.02553494897959183673469387755102041",
            "token":{
              "collection":{
                "symbol":"TAISTC",
                "name":"This Artwork Is Subject To Change"
              }
            }
          },
          {
            "senderAddress":{
              "id":"0xef528c12d521b5d7ea5c287b84c4ea682114a6d6"
            },
            "receiverAddress":{
              "id":"0x4326275317acc0fae4aa5c68fce4c54c74dc08d3"
            },
            "amount":"0.02553494897959183673469387755102041",
            "token":{
              "collection":{
                "symbol":"TAISTC",
                "name":"This Artwork Is Subject To Change"
              }
            }
          },
          {
            "senderAddress":{
              "id":"0x4326275317acc0fae4aa5c68fce4c54c74dc08d3"
            },
            "receiverAddress":{
              "id":"0xfcce36ad3b56647be372f90edaa4864fe32fc4b6"
            },
            "amount":"0",
            "token":{
              "collection":{
                "symbol":"TAISTC",
                "name":"This Artwork Is Subject To Change"
              }
            }
          }
        ],
        "transactionFrom":"0xfcce36ad3b56647be372f90edaa4864fe32fc4b6"
      },
      "platform":"X2Y2",
      "amount":"0.05106989795918367346938775510204082",
      "currency":{
        "name":"Ether",
        "symbol":"ETH"
      },
      "timestamp":1677131663,
      "blockNumber":16689149
    }
  },
  "27":{
    "sales":{
      "transaction":{
        "id":"0xbc61847a7f9aa94c80c5cdb7e626c3842430100f786deb3f124552398307d311",
        "transfers":[
          {
            "senderAddress":{
              "id":"0xef528c12d521b5d7ea5c287b84c4ea682114a6d6"
            },
            "receiverAddress":{
              "id":"0x4326275317acc0fae4aa5c68fce4c54c74dc08d3"
            },
            "amount":"0.05106989795918367346938775510204082",
            "token":{
              "collection":{
                "symbol":"TAISTC",
                "name":"This Artwork Is Subject To Change"
              }
            }
          },
          {
            "senderAddress":{
              "id":"0x4326275317acc0fae4aa5c68fce4c54c74dc08d3"
            },
            "receiverAddress":{
              "id":"0xfcce36ad3b56647be372f90edaa4864fe32fc4b6"
            },
            "amount":"0.02553494897959183673469387755102041",
            "token":{
              "collection":{
                "symbol":"TAISTC",
                "name":"This Artwork Is Subject To Change"
              }
            }
          },
          {
            "senderAddress":{
              "id":"0xef528c12d521b5d7ea5c287b84c4ea682114a6d6"
            },
            "receiverAddress":{
              "id":"0x4326275317acc0fae4aa5c68fce4c54c74dc08d3"
            },
            "amount":"0.02553494897959183673469387755102041",
            "token":{
              "collection":{
                "symbol":"TAISTC",
                "name":"This Artwork Is Subject To Change"
              }
            }
          },
          {
            "senderAddress":{
              "id":"0x4326275317acc0fae4aa5c68fce4c54c74dc08d3"
            },
            "receiverAddress":{
              "id":"0xfcce36ad3b56647be372f90edaa4864fe32fc4b6"
            },
            "amount":"0",
            "token":{
              "collection":{
                "symbol":"TAISTC",
                "name":"This Artwork Is Subject To Change"
              }
            }
          }
        ],
        "transactionFrom":"0xfcce36ad3b56647be372f90edaa4864fe32fc4b6"
      },
      "platform":"X2Y2",
      "amount":"0.05106989795918367346938775510204082",
      "currency":{
        "name":"Ether",
        "symbol":"ETH"
      },
      "timestamp":1677131663,
      "blockNumber":16689149
    }
  }
}